templates_service_client/__init__.py
templates_service_client/abstractions.py
templates_service_client/client.py
templates_service_client/validators.py
templates_service_client-0.0.1.dist-info/LICENSE
templates_service_client-0.0.1.dist-info/METADATA
templates_service_client-0.0.1.dist-info/WHEEL
templates_service_client-0.0.1.dist-info/top_level.txt
templates_service_client-0.0.1.dist-info/RECORD
