Metadata-Version: 2.1
Name: templates-service-client
Version: 0.0.1
Summary: A small client for templates service
Author-email: Alejandro <agarrido@izertis.com>
Classifier: Programming Language :: Python :: 3
Classifier: License :: OSI Approved :: MIT License
Classifier: Operating System :: OS Independent
Requires-Python: >=3.7
License-File: LICENSE
Requires-Dist: requests
Requires-Dist: dict-to-dataclass
Requires-Dist: pydantic
Requires-Dist: flask-pydantic-spec
Requires-Dist: Flask-Pydantic
